[
  {
    "level": 0,
    "label": "level zero",
    "description": "The effects (...) depend on the system and library implementation and may cause a program to behave in a non-standard manner or to terminate",
    "elements": [
      {
        "x": 0.00033,
        "y": 0.0001,
        "imgPath": "logos/reactlogo.png"
      },
      {
        "x": -1.013,
        "y": 1.12,
        "color": "#cba",
        "imgPath": "logos/chromelogo.png"
      }
    ]
  },
  {
    "level": 1,
    "label": "level one",
    "description": "Short forms of external names for systems with brain-damaged linkers.",
    "elements": [
      {
        "x": 0.00033,
        "y": 0.0001,
        "imgPath": "logos/reactlogo.png"
      },
      {
        "x": -1.013,
        "y": 1.12,
        "color": "#cba",
        "imgPath": "logos/chromelogo.png"
      }
    ]
  },
  {
    "level": 2,
    "label": "level two",
    "description": "The kernel is free to ignore the advice.",
    "elements": [
      {
        "x": 0.00033,
        "y": 0.0001,
        "imgPath": "logos/reactlogo.png"
      },
      {
        "x": -1.013,
        "y": 1.12,
        "color": "#cba",
        "imgPath": "logos/chromelogo.png"
      }
    ]
  },
  {
    "level": 3,
    "label": "level three",
    "description": "This is not the function you are interested in.",
    "elements": [
      {
        "x": 0.00033,
        "y": 0.0001,
        "imgPath": "logos/reactlogo.png"
      },
      {
        "x": -1.013,
        "y": 1.12,
        "color": "#cba",
        "imgPath": "logos/chromelogo.png"
      }
    ]
  },
  {
    "level": 2,
    "label": "level four",
    "description": "Autogenerated, do not edit. All changes will be undone.",
    "elements": [
      {
        "x": 0.00033,
        "y": 0.0001,
        "imgPath": "logos/reactlogo.png"
      },
      {
        "x": -1.013,
        "y": 1.12,
        "color": "#cba",
        "imgPath": "logos/chromelogo.png"
      }
    ]
  },
  {
    "level": 2,
    "label": "level five",
    "description": "Should neve happen",
    "elements": [
      {
        "x": 0.00033,
        "y": 0.0001,
        "imgPath": "logos/reactlogo.png"
      },
      {
        "x": -1.013,
        "y": 1.12,
        "color": "#cba",
        "imgPath": "logos/chromelogo.png"
      }
    ]
  },
  {
    "level": 2,
    "label": "level six",
    "description": "Magic. Do not touch.",
    "elements": [
      {
        "x": 0.00033,
        "y": 0.0001,
        "imgPath": "logos/reactlogo.png"
      },
      {
        "x": -1.013,
        "y": 1.12,
        "color": "#cba",
        "imgPath": "logos/chromelogo.png"
      }
    ]
  },
  {
    "level": 2,
    "label": "level seven",
    "description": "Replaces with spaces the braces in cases where braces in places cause stasis",
    "elements": [
      {
        "x": 0.00033,
        "y": 0.0001,
        "imgPath": "logos/reactlogo.png"
      },
      {
        "x": -1.013,
        "y": 1.12,
        "color": "#cba",
        "imgPath": "logos/chromelogo.png"
      }
    ]
  }
]